cntrlai/__init__.py
cntrlai/batch_evaluation.py
cntrlai/guardrails.py
cntrlai/langchain.py
cntrlai/logger.py
cntrlai/openai.py
cntrlai/types.py
cntrlai/utils.py
cntrlai-0.0.34.dist-info/METADATA
cntrlai-0.0.34.dist-info/WHEEL
cntrlai-0.0.34.dist-info/RECORD
