Metadata-Version: 2.1
Name: cntrlai
Version: 0.0.34
Summary: ControlAI's Client for Monitoring Your LLM performance
Home-page: https://controlai.org
License: MIT
Author: Lukasz Bartoszcze
Author-email: lbartoszcze@controlai.org
Requires-Python: >=3.9,<4.0
Classifier: Development Status :: 4 - Beta
Classifier: Intended Audience :: Developers
Classifier: License :: OSI Approved :: MIT License
Classifier: Operating System :: OS Independent
Classifier: Programming Language :: Python :: 3
Classifier: Programming Language :: Python :: 3.9
Classifier: Programming Language :: Python :: 3.10
Classifier: Programming Language :: Python :: 3.11
Classifier: Programming Language :: Python :: 3.12
Classifier: Topic :: Software Development :: Libraries :: Python Modules
Provides-Extra: langchain
Provides-Extra: openai
Requires-Dist: httpx (>=0.27.0,<0.28.0)
Requires-Dist: langchain (>=0.0.345,<0.0.346) ; extra == "langchain"
Requires-Dist: nanoid (>=2.0.0,<3.0.0)
Requires-Dist: openai (>=1.3.7,<2.0.0) ; extra == "openai"
Requires-Dist: pandas (>=2.2.2,<3.0.0)
Requires-Dist: pydantic (>=2.5.2)
Requires-Dist: requests (>=2.31.0,<3.0.0)
Requires-Dist: retry (>=0.9.2,<0.10.0)
Requires-Dist: tqdm (>=4.66.2,<5.0.0)
Project-URL: Main App, https://controlai.org
